{
  "project_info": {
    "project_number": "352760787087",
    "firebase_url": "https://reactionspeedtrainer-default-rtdb.europe-west1.firebasedatabase.app",
    "project_id": "reactionspeedtrainer",
    "storage_bucket": "reactionspeedtrainer.firebasestorage.app"
  },
  "client": [
    {
      "client_info": {
        "mobilesdk_app_id": "1:352760787087:android:dc345ed90a6639ff5a80fa",
        "android_client_info": {
          "package_name": "com.example.reaction_speed_trainer"
        }
      },
      "oauth_client": [],
      "api_key": [
        {
          "current_key": "AIzaSyBK0kkd0MTeCcnP5XFD4yQWgnw7T8voxgg"
        }
      ],
      "services": {
        "appinvite_service": {
          "other_platform_oauth_client": []
        }
      }
    }
  ],
  "configuration_version": "1"
}